tree_sitter_robot-1.1.2.dist-info/RECORD
tree_sitter_robot-1.1.2.dist-info/WHEEL
tree_sitter_robot-1.1.2.dist-info/top_level.txt
tree_sitter_robot-1.1.2.dist-info/METADATA
tree_sitter_robot-1.1.2.dist-info/licenses/LICENSE
tree_sitter_robot/__init__.pyi
tree_sitter_robot/binding.c
tree_sitter_robot/__init__.py
tree_sitter_robot/py.typed
tree_sitter_robot/_binding.abi3.so
tree_sitter_robot/queries/indents.scm
tree_sitter_robot/queries/highlights.scm
tree_sitter_robot/queries/folds.scm
